Workbook
Name Années: _xlfn.ANCHORARRAY(Listes!$H$11)
Name Entreprise: Balises!$E$6
Name Loop_parameters: Charts_settings!$B$6:$E$6
Name Périodes: Balises!$E$6
Name s_produit: Charts_settings!$E$6
Name siren: Balises!$E$7

Sheet DONNÉES BRUTES

Sheet Performance
A1: siren | B1: date_cloture_exercice | C1: Chiffre_d_affaires | D1: Marge_brute | E1: EBE | F1: EBIT | G1: Resultat_net | H1: Taux_d_endettement | I1: Ratio_de_liquidite | J1: Ratio_de_vetuste | K1: Autonomie_financiere | L1: Poids_BFR_exploitation_sur_CA | M1: Couverture_des_interets | N1: CAF_sur_CA | O1: Capacite_de_remboursement | P1: Marge_EBE | Q1: Resultat_courant_avant_impots_sur_CA | R1: Poids_BFR_exploitation_sur_CA_jours | S1: Rotation_des_stocks_jours | T1: Credit_clients_Jours | U1: Credit_fournisseurs_Jours | V1: type_bilan | W1: confidentiality
A2: 476480330 | B2: 44196 | C2: 64657526 | D2: 34888091 | E2: -6041459 | F2: -4020920 | G2: -2924242 | H2: -1553049 | I2: 48635 | J2: 19,46 | K2: -1111 | L2: -14596 | M2: -8323 | N2: -12127 | O2: -0,994 | P2: -9344 | Q2: -6982 | R2: -52544 | S2: 25959 | T2: 42758 | U2: 77587 | V2: C | W2: Public

Sheet SETTINGS

Sheet Listes
B10: SIREN | C10: Nom | D10: Activité | E10: Activité détaillée | F10: CA | H10: Années
A11: {=_xlfn.SEQUENCE(COUNTA(_xlfn.UNIQUE(Performance[siren])))} -> 1 | B11: {=_xlfn.UNIQUE(Performance[siren])} -> 476480330 | C11: {=INDEX(#REF!,MATCH(_xlfn.ANCHORARRAY($B$11),Performance[siren],0))} -> #REF! | D11: {=INDEX(#REF!,MATCH(_xlfn.ANCHORARRAY($B$11),Performance[siren],0))} -> #REF! | E11: {=INDEX(#REF!,MATCH(_xlfn.ANCHORARRAY($B$11),Performance[siren],0))} -> #REF! | F11: {=SUMIFS(Performance[Chiffre_d_affaires],Performance[siren],Listes!$B$11:$B$676)} -> 64657526 | H11: {=_xlfn.SORTBY(_xlfn._xlws.FILTER(Performance[date_cloture_exercice],#REF!=Entreprise),_xlfn._xlws.FILTER(Performance[date_cloture_exercice],#REF!=Entreprise),1)} -> #REF!
F12: 0
F13: 0
F14: 0
F15: 0
F16: 0
F17: 0
F18: 0
F19: 0
F20: 0
F21: 0
F22: 0
F23: 0
... F676: 0

Sheet Image
A1: Activité | B1: Activité détaillée | C1: Picture
A2: Fabrication d’huiles et graisses végétales et animales | B2: Fabrication de margarine et graisses comestibles similaires | C2: Graisses
A3: Fabrication d’huiles et graisses végétales et animales | B3: Fabrication d'huiles et graisses brutes | C3: Graisses
A4: Fabrication d’huiles et graisses végétales et animales | B4: Fabrication d'huiles et graisses raffinées | C4: Graisses
A5: Fabrication d'autres produits alimentaires | B5: Fabrication d'aliments homogénéisés et diététiques | C5: Cuisine
A6: Fabrication d'autres produits alimentaires | B6: Fabrication d'autres produits alimentaires n.c.a. | C6: Cuisine
A7: Fabrication d'autres produits alimentaires | B7: Fabrication de cacao, chocolat et de produits de confiserie | C7: Cacao
A8: Fabrication d'autres produits alimentaires | B8: Fabrication de condiments et assaisonnements | C8: Cuisine
A9: Fabrication d'autres produits alimentaires | B9: Fabrication de plats préparés | C9: Cuisine
A10: Fabrication d'autres produits alimentaires | B10: Fabrication de sucre | C10: Sucre
A11: Fabrication d'autres produits alimentaires | B11: Transformation du thé et du café | C11: Café
A12: Fabrication de boissons | B12: Fabrication de bière | C12: Bière
... A40: Travail des grains ; fabrication de produits amylacés | B40: Meunerie | C40: Grains

Sheet Balises
D2: Balise de suppression de la slide | E2: [@SUPR@]
C4: Balise | D4: Desc | E4: Valeur
C5: [Incohérence] | D5: Suppression de la slide | E5: =IF(OR(Balises!$E$8>=1,Balises!$E$9>=1),Balises!$E$2,"") -> #REF!
C6: [Entreprise] | D6: Nom de l'entreprise | E6: =s_produit -> #REF!
C7: [Siren] | D7: Siren | E7: =INDEX(Performance[siren],MATCH(Entreprise,#REF!,0)) -> #REF!
C8: [EBE] | D8: EBE | E8: =Analyse!$AA$4 -> #REF!
C9: [RN_p] | D9: Résultat net en % | E9: =Analyse!$AA$5 -> #REF!
C10: [RN] | D10: résultat net | E10: =SUMIFS(Performance[Resultat_net],#REF!,Entreprise,Performance[date_cloture_exercice],Analyse!$E$3) -> #REF!
C11: [CA] | D11: Chiffre d'affaires dernière année | E11: =INDEX(_xlfn.ANCHORARRAY(Analyse!$C$7),MATCH($E$15,_xlfn.ANCHORARRAY(Analyse!$E$7),0)) -> #REF!
C12: [Cagr_CA] | D12: Croissance annuelle du CA | E12: =Analyse!$G$4 -> NA
C13: [Cagr_EBE] | D13: Croissance annuellee de l'EBE | E13: =Analyse!$R$4 -> NA
C14: [Start] | D14: Première année | E14: =MIN(_xlfn.ANCHORARRAY(Analyse!$E$7)) -> #REF!
C15: [End] | D15: Dernière année | E15: =MAX(_xlfn.ANCHORARRAY(Analyse!$E$7)) -> #REF!
C16: [Famille] | E16: =INDEX(#REF!,MATCH(siren,Performance[siren],0)) -> #REF!
C17: [Segment] | E17: =INDEX(#REF!,MATCH(siren,Performance[siren],0)) -> #REF!
C18: [Background] | E18: =INDEX(Image!$C:$C,MATCH($E$17,Image!B:B,0)) -> #REF!
C19: [Date] | D19: Date de génération | E19: =TODAY() -> 45935

Sheet Charts_settings
B2: Distributeur | C2: France
B3: Marque | C3: All
B5: ID | C5: Itération | D5: Nombre de tests | E5: Résultat
B6: Entreprise | C6: 1 | D6: 4 | E6: {=INDEX(Listes!$C$11:$C$676,Loop[[#This Row],[Itération]])} -> #REF!

Sheet Analyse
E2: =MIN(_xlfn.ANCHORARRAY(B7)) -> #REF! | F2: =MIN(_xlfn.ANCHORARRAY($E$7)) -> #REF! | G2: =INDEX(_xlfn.ANCHORARRAY(C$7),MATCH(F2,_xlfn.ANCHORARRAY(E$7),0)) -> #REF! | Q2: =MIN(_xlfn.ANCHORARRAY($E$7)) -> #REF! | R2: =INDEX(_xlfn.ANCHORARRAY(N$7),MATCH(Q2,_xlfn.ANCHORARRAY(P$7),0)) -> #REF!
E3: =MAX(_xlfn.ANCHORARRAY(B7)) -> #REF! | F3: =MAX(_xlfn.ANCHORARRAY($E$7)) -> #REF! | G3: =INDEX(_xlfn.ANCHORARRAY(C$7),MATCH(F3,_xlfn.ANCHORARRAY(E$7),0)) -> #REF! | Q3: =MAX(_xlfn.ANCHORARRAY($E$7)) -> #REF! | R3: =INDEX(_xlfn.ANCHORARRAY(N$7),MATCH(Q3,_xlfn.ANCHORARRAY(P$7),0)) -> #REF! | AH3: Base | AI3: Blank | AJ3: Increase | AK3: Decrease
B4: =Entreprise -> #REF! | F4: ="CAGR entre "&$F$2&" et "&$F$3 -> #REF! | G4: =IFERROR((G3/G2)^(1/(F3-F2))-1,"NA") -> NA | M4: =Entreprise -> #REF! | Q4: ="CAGR entre "&$F$2&" et "&$F$3 -> #REF! | R4: =IFERROR((R3/R2)^(1/(Q3-Q2))-1,"NA") -> NA | Z4: Taux EBE | AA4: =SUMIFS(Performance[EBE],#REF!,Entreprise,Performance[date_cloture_exercice],$E$3)/ SUMIFS(Performance[Chiffre_d_affaires],#REF!,Entreprise,Performance[date_cloture_exercice],$E$3) -> #REF! | AB4: =1-AA4 -> #REF! | AE4: Chiffre d'affaires | AF4: =SUMIFS(Performance[Chiffre_d_affaires],#REF!,Entreprise,Performance[date_cloture_exercice],$E$3) -> #REF! | AG4: =AF4/$AF$4 -> #REF! | AH4: =AG4 -> #REF!
Z5: Résultat net | AA5: =SUMIFS(Performance[Resultat_net],#REF!,Entreprise,Performance[date_cloture_exercice],$E$3)/ SUMIFS(Performance[Chiffre_d_affaires],#REF!,Entreprise,Performance[date_cloture_exercice],$E$3) -> #REF! | AB5: =1-AA5 -> #REF! | AE5: Marchandises et M1 | AF5: =AF6-AF4 -> #REF! | AG5: =AF5/$AF$4 -> #REF! | AI5: =AH6 -> #REF! | AJ5: =IF($AG5>0,$AG5,0) -> #REF! | AK5: =ABS(IF($AG5<0,$AG5,0)) -> #REF!
B6: Date | C6: Chiffre d'affaires | D6: Année prec | E6: Année | F6: Precédente valeur | G6: CAGR | H6: Positive | I6: Negative | J6: Text | M6: Date | N6: EBE | O6: Année prec | P6: Année | Q6: Precédente valeur | R6: CAGR | S6: Positive | T6: Negative | U6: Text | V6: EBE | W6: Taux de marge | AE6: Marge brute | AF6: =SUMIFS(Performance[Marge_brute],#REF!,Entreprise,Performance[date_cloture_exercice],$E$3) -> #REF! | AG6: =AF6/$AF$4 -> #REF! | AH6: =AG6 -> #REF!
B7: {=Années} -> #REF! | C7: {=SUMIFS(Performance[Chiffre_d_affaires],#REF!,Entreprise,Performance[date_cloture_exercice],_xlfn.ANCHORARRAY($B7))} -> #REF! | D7: {=IF(_xlfn.ANCHORARRAY($E$7)=$F$2,0,IFERROR(YEAR(INDEX(_xlfn.ANCHORARRAY(B7),_xlfn.SEQUENCE(COUNTA(_xlfn.ANCHORARRAY($B$7)))-1)),0))} -> #REF! | E7: {=YEAR(_xlfn.ANCHORARRAY(B7))} -> #REF! | F7: {=IF(_xlfn.ANCHORARRAY($E$7)=$F$2,0,IFERROR(INDEX(_xlfn.ANCHORARRAY($C$7),_xlfn.SEQUENCE(COUNTA(_xlfn.ANCHORARRAY($B$7)))-1),0))} -> #REF! | G7: {=IFERROR((_xlfn.ANCHORARRAY(C7)/_xlfn.ANCHORARRAY(F7))^(1/(_xlfn.ANCHORARRAY(E7)-_xlfn.ANCHORARRAY(D7)))-1,0)} -> 0 | H7: {=IF(_xlfn.ANCHORARRAY(G7)>0,1,NA())} -> #N/A | I7: {=IF(_xlfn.ANCHORARRAY(G7)<0,1,NA())} -> #N/A | J7: {=IF(((_xlfn.ANCHORARRAY(E7)=_xlfn.ANCHORARRAY(D7)+1)+(_xlfn.ANCHORARRAY(D7)=0)>0),"","CAGR "&_xlfn.ANCHORARRAY(D7)&" ")&TEXT(_xlfn.ANCHORARRAY(G7),"+0%;-0%;-")} -> #REF! | M7: {=Années} -> #REF! | N7: {=SUMIFS(Performance[EBE],#REF!,Entreprise,Performance[date_cloture_exercice],_xlfn.ANCHORARRAY($B7))} -> #REF! | O7: {=IF(_xlfn.ANCHORARRAY($E$7)=$F$2,0,IFERROR(YEAR(INDEX(_xlfn.ANCHORARRAY(M7),_xlfn.SEQUENCE(COUNTA(_xlfn.ANCHORARRAY($B$7)))-1)),0))} -> #REF! | P7: {=YEAR(_xlfn.ANCHORARRAY(M7))} -> #REF! | Q7: {=IF(_xlfn.ANCHORARRAY(P7)=$F$2,0,IFERROR(INDEX(_xlfn.ANCHORARRAY(N7),_xlfn.SEQUENCE(COUNTA(_xlfn.ANCHORARRAY(M7)))-1),0))} -> #REF! | R7: {=IFERROR((_xlfn.ANCHORARRAY(N7)/_xlfn.ANCHORARRAY(Q7))^(1/(_xlfn.ANCHORARRAY(P7)-_xlfn.ANCHORARRAY(O7)))-1,0)} -> 0 | S7: {=IF(_xlfn.ANCHORARRAY(R7)>0,1,NA())} -> #N/A | T7: {=IF(_xlfn.ANCHORARRAY(R7)<0,1,NA())} -> #N/A | U7: {=IF(((_xlfn.ANCHORARRAY(P7)=_xlfn.ANCHORARRAY(O7)+1)+(_xlfn.ANCHORARRAY(O7)=0)>0),"","CAGR "&_xlfn.ANCHORARRAY(O7)&" ")&TEXT(_xlfn.ANCHORARRAY(R7),"+0%;-0%;-")} -> #REF! | V7: {=SUMIFS(Performance[EBE],#REF!,Entreprise,Performance[date_cloture_exercice],_xlfn.ANCHORARRAY($B7))} -> #REF! | W7: {=_xlfn.ANCHORARRAY(V7)/_xlfn.ANCHORARRAY(C7)} -> #REF! | AE7: Production (salaire, ext.) | AF7: =AF8-AF6 -> #REF! | AG7: =AF7/$AF$4 -> #REF! | AI7: =AH8 -> #REF! | AJ7: =IF($AG7>0,$AG7,0) -> #REF! | AK7: =ABS(IF($AG7<0,$AG7,0)) -> #REF!
AE8: EBE | AF8: =SUMIFS(Performance[EBE],#REF!,Entreprise,Performance[date_cloture_exercice],$E$3) -> #REF! | AG8: =AF8/$AF$4 -> #REF! | AH8: =AG8 -> #REF!
AE9: Exceptionnel | AF9: =AF10-AF8 -> #REF! | AG9: =AF9/$AF$4 -> #REF! | AI9: =AH10 -> #REF! | AJ9: =IF($AG9>0,$AG9,0) -> #REF! | AK9: =ABS(IF($AG9<0,$AG9,0)) -> #REF!
AE10: Résultat net | AF10: =SUMIFS(Performance[Resultat_net],#REF!,Entreprise,Performance[date_cloture_exercice],$E$3) -> #REF! | AG10: =AF10/$AF$4 -> #REF! | AH10: =AG10 -> #REF!

Sheet Table
